LICENSE
MANIFEST.in
README.rst
setup.py
bin/xmppcat
xmppcat/__init__.py
xmppcat/__main__.py
xmppcat/bot.py
xmppcat.egg-info/PKG-INFO
xmppcat.egg-info/SOURCES.txt
xmppcat.egg-info/dependency_links.txt
xmppcat.egg-info/requires.txt
xmppcat.egg-info/top_level.txt