Metadata-Version: 1.1
Name: xmppcat
Version: 0.1.1
Summary: CLI application that works like cat but sends its output through xmpp
Home-page: http://github.com/mtorromeo/xmppcat
Author: Massimiliano Torromeo
Author-email: massimiliano.torromeo@gmail.com
License: BSD License
Download-URL: http://github.com/mtorromeo/xmppcat/tarball/v0.1.1
Platform: UNKNOWN
Classifier: Programming Language :: Python
Classifier: Programming Language :: Python :: 3
Classifier: Development Status :: 4 - Beta
Classifier: License :: OSI Approved :: BSD License
Classifier: Operating System :: MacOS :: MacOS X
Classifier: Operating System :: POSIX :: Linux
Classifier: Operating System :: POSIX :: BSD
Classifier: Natural Language :: English
